{
  "kind": "collectionType",
  "collectionName": "creative_works",
  "info": {
    "singularName": "creative-work",
    "pluralName": "creative-works",
    "displayName": "Creative Work",
    "description": "Films, plays, short films, concerts, exhibitions and other creative works"
  },
  "options": {
    "draftAndPublish": true
  },
  "pluginOptions": {
    "i18n": {
      "localized": true
    }
  },
  "attributes": {
    "title": {
      "type": "string",
      "required": true,
      "pluginOptions": {
        "i18n": {
          "localized": true
        }
      }
    },
    "originalTitle": {
      "type": "string",
      "pluginOptions": {
        "i18n": {
          "localized": false
        }
      }
    },
    "slug": {
      "type": "uid",
      "targetField": "title",
      "pluginOptions": {
        "i18n": {
          "localized": false
        }
      }
    },
    "type": {
      "type": "enumeration",
      "enum": ["film", "play", "short-film", "concert", "exhibition"],
      "required": true,
      "pluginOptions": {
        "i18n": {
          "localized": false
        }
      }
    },
    "synopsis": {
      "type": "richtext",
      "pluginOptions": {
        "i18n": {
          "localized": true
        }
      }
    },
    "duration": {
      "type": "integer",
      "pluginOptions": {
        "i18n": {
          "localized": false
        }
      }
    },
    "releaseYear": {
      "type": "integer",
      "pluginOptions": {
        "i18n": {
          "localized": false
        }
      }
    },
    "genres": {
      "type": "relation",
      "relation": "manyToMany",
      "target": "plugin::creative-works.genre"
    },
    "directors": {
      "type": "relation",
      "relation": "manyToMany",
      "target": "plugin::creative-works.person"
    },
    "cast": {
      "type": "component",
      "repeatable": true,
      "component": "creative-works.cast",
      "pluginOptions": {
        "i18n": {
          "localized": false
        }
      }
    },
    "crew": {
      "type": "component",
      "repeatable": true,
      "component": "creative-works.credit",
      "pluginOptions": {
        "i18n": {
          "localized": false
        }
      }
    },
    "poster": {
      "type": "media",
      "multiple": false,
      "required": false,
      "allowedTypes": ["images"],
      "pluginOptions": {
        "i18n": {
          "localized": true
        }
      }
    },
    "backdrop": {
      "type": "media",
      "multiple": false,
      "required": false,
      "allowedTypes": ["images"],
      "pluginOptions": {
        "i18n": {
          "localized": false
        }
      }
    },
    "photos": {
      "type": "media",
      "multiple": true,
      "required": false,
      "allowedTypes": ["images"],
      "pluginOptions": {
        "i18n": {
          "localized": false
        }
      }
    },
    "trailer": {
      "type": "string",
      "pluginOptions": {
        "i18n": {
          "localized": false
        }
      }
    },
    "videos": {
      "type": "component",
      "repeatable": true,
      "component": "common.video",
      "pluginOptions": {
        "i18n": {
          "localized": false
        }
      }
    },
    "rating": {
      "type": "decimal",
      "pluginOptions": {
        "i18n": {
          "localized": false
        }
      }
    },
    "ageRating": {
      "type": "enumeration",
      "enum": ["TP", "PG12", "PG16", "PG18"],
      "pluginOptions": {
        "i18n": {
          "localized": false
        }
      }
    },
    "facts": {
      "type": "component",
      "repeatable": true,
      "component": "common.remarkable-fact",
      "pluginOptions": {
        "i18n": {
          "localized": true
        }
      }
    },
    "links": {
      "type": "component",
      "repeatable": true,
      "component": "common.social-link",
      "pluginOptions": {
        "i18n": {
          "localized": false
        }
      }
    }
  }
}
